overkiz_runner/__init__.py
overkiz_runner/__main__.py
overkiz_runner/configuration.py
overkiz_runner/dwh.py
overkiz_runner/printer.py
overkiz_runner/utils.py
overkiz_runner-0.0.5.dist-info/METADATA
overkiz_runner-0.0.5.dist-info/WHEEL
overkiz_runner-0.0.5.dist-info/RECORD
