Metadata-Version: 2.3
Name: overkiz-runner
Version: 0.0.5
Summary: 
Requires-Python: >=3.12,<4.0
Classifier: Development Status :: 5 - Production/Stable
Classifier: Topic :: Home Automation
Classifier: Topic :: System :: Monitoring
Requires-Dist: pyoverkiz
Requires-Dist: the-conf (>=1.0.3)
